djangoldp_esa/__init__.py
djangoldp_esa/admin.py
djangoldp_esa/apps.py
djangoldp_esa/models.py
djangoldp_esa/settings.py
djangoldp_esa/migrations/0001_initial.py
djangoldp_esa/migrations/0002_auto_20220623_1611.py
djangoldp_esa/migrations/0003_auto_20220627_1354.py
djangoldp_esa/migrations/0004_alter_esabiclocation_options_and_more.py
djangoldp_esa/migrations/0005_esabiclocation_created_at_esabiclocation_updated_at_and_more.py
djangoldp_esa/migrations/__init__.py
djangoldp_esa/templates/email.html
djangoldp_esa/templates/admin/login.html
djangoldp_esa/templates/oidc_provider/authorize.html
djangoldp_esa/templates/password/email.html
djangoldp_esa/templates/registration/login.html
djangoldp_esa/templates/registration/password_reset_confirm.html
djangoldp_esa/templates/registration/password_reset_done.html
djangoldp_esa/templates/registration/password_reset_email.html
djangoldp_esa/templates/registration/password_reset_form.html
djangoldp_esa-3.0.0.dist-info/METADATA
djangoldp_esa-3.0.0.dist-info/WHEEL
djangoldp_esa-3.0.0.dist-info/top_level.txt
djangoldp_esa-3.0.0.dist-info/RECORD
