Metadata-Version: 2.4
Name: djangoldp_esa
Version: 3.0.0
Summary: djangoldp package for ESA
Home-page: https://git.startinblox.com/djangoldp-packages/djangoldp-esa
Author: Startin'blox
Author-email: jbaptiste@startinblox.com
License: MIT
Requires-Dist: djangoldp~=5.0.0
Provides-Extra: include-package-data
Requires-Dist: True; extra == "include-package-data"
